iter_tools/__init__.py
iter_tools/sel.py
iter_tools-0.0.2.dist-info/LICENSE
iter_tools-0.0.2.dist-info/METADATA
iter_tools-0.0.2.dist-info/WHEEL
iter_tools-0.0.2.dist-info/top_level.txt
iter_tools-0.0.2.dist-info/RECORD
