Metadata-Version: 2.1
Name: iter-tools
Version: 0.0.2
Summary: Tool for iterations.
Home-page: https://github.com/Lion-UY/iter-tools
Author: Zecyel & Lion-UY
Author-email: zecyel@163.com
Classifier: Programming Language :: Python :: 3
Classifier: License :: OSI Approved :: MIT License
Classifier: Operating System :: OS Independent
Requires-Python: >=3.6
License-File: LICENSE
